{"data":{"node":{"binaries":{"edges":[{"node":{"change_log":"N/A","id":"1098779963491299","version":"1","version_code":2,"created_date":1475176568}},{"node":{"change_log":"N/A","id":"1039332142769415","version":"0.9","version_code":1,"created_date":1468418390}}]},"latest_supported_binary":{"binary_application":{"display_name":""}},"appName":"DRIFT","headset":"RIFT","squareImage":"https://scontent.oculuscdn.com/v/t64.5771-25/q92/s720x720/12448852_264394380607788_1744439269_n.jpg?_nc_cat=104\u0026ccb=1-5\u0026_nc_sid=79b88e\u0026_nc_ohc=bni1zRq_18AAX9O5LpU\u0026_nc_ht=scontent.oculuscdn.com\u0026oh=df75deb787b4483d9fd04abc6637da58\u0026oe=6133257E","id":"1029793527056610"}}}