{"data":{"node":{"binaries":{"edges":[{"node":{"change_log":"N/A","id":"2318587358234899","version":"2.3.1","version_code":126,"created_date":1559026323}},{"node":{"change_log":"N/A","id":"2065614173532220","version":"2.2.2","version_code":125,"created_date":1544730500}},{"node":{"change_log":"N/A","id":"2061758620584442","version":"2.2.1","version_code":124,"created_date":1544516864}},{"node":{"change_log":"N/A","id":"2025315570895414","version":"2.2.0","version_code":120,"created_date":1542320744}},{"node":{"change_log":"N/A","id":"1938979442862361","version":"2.1.8","version_code":116,"created_date":1537265522}},{"node":{"change_log":"N/A","id":"1929432730483699","version":"2.1.6","version_code":114,"created_date":1536660734}},{"node":{"change_log":"N/A","id":"1920306824729623","version":".01preorder","version_code":109,"created_date":1536176155}}]},"latest_supported_binary":{"binary_application":{"display_name":""}},"appName":"Windlands 2","headset":"RIFT","squareImage":"https://scontent.oculuscdn.com/v/t64.5771-25/q92/s720x720/11162771_1579948652062786_6230698787040395264_n.jpg?_nc_cat=109\u0026ccb=1-3\u0026_nc_sid=79b88e\u0026_nc_ohc=8vmbtNUrtToAX86-DI4\u0026_nc_ht=scontent.oculuscdn.com\u0026oh=824c1832801a9844ab21fd72b7c7dda9\u0026oe=60F9FC64","id":"1087949831298664"}}}