{"data":{"node":{"binaries":{"edges":[{"node":{"id":"1361462587221175","version":"1.10","platform":"","file_name":"MagnetiqueGear_13_12.apk","uri":"","change_log":"","changeLog":"","richChangeLog":"","binary_application":{"primary_binaries":{"count":0,"edges":[]},"id":"","platform":"","display_name":"","displayName":"","release_channels":{"count":0,"nodes":[]},"revisions":{"count":0,"nodes":[]},"organization":{"id":"","is_authorized_for_quest":false},"is_concept":false,"is_approved":false,"is_enterprise_enabled":false,"canonicalName":"","release_date":0,"viewer_has_preorder":false,"cover_landscape_image":{"uri":""},"cover_portrait_image":{"uri":""},"cover_square_image":{"uri":""},"screenshots":[],"supportedBinaries":{"count":0,"edges":[]}},"__isAppBinary":"","__isAppBinaryWithFileAsset":"","version_code":10,"versionCode":10,"created_date":1481624920,"binary_release_channels":{"count":0,"nodes":[{"id":"1700850070180525","channel_name":"LIVE","latest_supported_binary":{"id":"","version":"","platform":"","file_name":"","uri":"","change_log":"","changeLog":"","richChangeLog":"","binary_application":{"primary_binaries":{"count":0,"edges":[]},"id":"","platform":"","display_name":"","displayName":"","release_channels":{"count":0,"nodes":[]},"revisions":{"count":0,"nodes":[]},"organization":{"id":"","is_authorized_for_quest":false},"is_concept":false,"is_approved":false,"is_enterprise_enabled":false,"canonicalName":"","release_date":0,"viewer_has_preorder":false,"cover_landscape_image":{"uri":""},"cover_portrait_image":{"uri":""},"cover_square_image":{"uri":""},"screenshots":[],"supportedBinaries":{"count":0,"edges":[]}},"__isAppBinary":"","__isAppBinaryWithFileAsset":"","version_code":0,"versionCode":0,"created_date":0,"binary_release_channels":null,"__typename":""}}]},"__typename":"AndroidBinary"}},{"node":{"id":"1361445530556214","version":"1.09","platform":"","file_name":"MagnetiqueGear_13_12.apk","uri":"","change_log":"","changeLog":"","richChangeLog":"","binary_application":{"primary_binaries":{"count":0,"edges":[]},"id":"","platform":"","display_name":"","displayName":"","release_channels":{"count":0,"nodes":[]},"revisions":{"count":0,"nodes":[]},"organization":{"id":"","is_authorized_for_quest":false},"is_concept":false,"is_approved":false,"is_enterprise_enabled":false,"canonicalName":"","release_date":0,"viewer_has_preorder":false,"cover_landscape_image":{"uri":""},"cover_portrait_image":{"uri":""},"cover_square_image":{"uri":""},"screenshots":[],"supportedBinaries":{"count":0,"edges":[]}},"__isAppBinary":"","__isAppBinaryWithFileAsset":"","version_code":9,"versionCode":9,"created_date":1481623916,"binary_release_channels":{"count":0,"nodes":[{"id":"1700850070180525","channel_name":"LIVE","latest_supported_binary":{"id":"","version":"","platform":"","file_name":"","uri":"","change_log":"","changeLog":"","richChangeLog":"","binary_application":{"primary_binaries":{"count":0,"edges":[]},"id":"","platform":"","display_name":"","displayName":"","release_channels":{"count":0,"nodes":[]},"revisions":{"count":0,"nodes":[]},"organization":{"id":"","is_authorized_for_quest":false},"is_concept":false,"is_approved":false,"is_enterprise_enabled":false,"canonicalName":"","release_date":0,"viewer_has_preorder":false,"cover_landscape_image":{"uri":""},"cover_portrait_image":{"uri":""},"cover_square_image":{"uri":""},"screenshots":[],"supportedBinaries":{"count":0,"edges":[]}},"__isAppBinary":"","__isAppBinaryWithFileAsset":"","version_code":0,"versionCode":0,"created_date":0,"binary_release_channels":null,"__typename":""}}]},"__typename":"AndroidBinary"}},{"node":{"id":"1360597290641038","version":"1.08","platform":"","file_name":"Magnetique_12_12.apk","uri":"","change_log":"","changeLog":"","richChangeLog":"","binary_application":{"primary_binaries":{"count":0,"edges":[]},"id":"","platform":"","display_name":"","displayName":"","release_channels":{"count":0,"nodes":[]},"revisions":{"count":0,"nodes":[]},"organization":{"id":"","is_authorized_for_quest":false},"is_concept":false,"is_approved":false,"is_enterprise_enabled":false,"canonicalName":"","release_date":0,"viewer_has_preorder":false,"cover_landscape_image":{"uri":""},"cover_portrait_image":{"uri":""},"cover_square_image":{"uri":""},"screenshots":[],"supportedBinaries":{"count":0,"edges":[]}},"__isAppBinary":"","__isAppBinaryWithFileAsset":"","version_code":8,"versionCode":8,"created_date":1481546979,"binary_release_channels":{"count":0,"nodes":[{"id":"1700850070180525","channel_name":"LIVE","latest_supported_binary":{"id":"","version":"","platform":"","file_name":"","uri":"","change_log":"","changeLog":"","richChangeLog":"","binary_application":{"primary_binaries":{"count":0,"edges":[]},"id":"","platform":"","display_name":"","displayName":"","release_channels":{"count":0,"nodes":[]},"revisions":{"count":0,"nodes":[]},"organization":{"id":"","is_authorized_for_quest":false},"is_concept":false,"is_approved":false,"is_enterprise_enabled":false,"canonicalName":"","release_date":0,"viewer_has_preorder":false,"cover_landscape_image":{"uri":""},"cover_portrait_image":{"uri":""},"cover_square_image":{"uri":""},"screenshots":[],"supportedBinaries":{"count":0,"edges":[]}},"__isAppBinary":"","__isAppBinaryWithFileAsset":"","version_code":0,"versionCode":0,"created_date":0,"binary_release_channels":null,"__typename":""}}]},"__typename":"AndroidBinary"}},{"node":{"id":"1262688207098614","version":"1.01","platform":"","file_name":"Magne01.apk","uri":"","change_log":"","changeLog":"","richChangeLog":"","binary_application":{"primary_binaries":{"count":0,"edges":[]},"id":"","platform":"","display_name":"","displayName":"","release_channels":{"count":0,"nodes":[]},"revisions":{"count":0,"nodes":[]},"organization":{"id":"","is_authorized_for_quest":false},"is_concept":false,"is_approved":false,"is_enterprise_enabled":false,"canonicalName":"","release_date":0,"viewer_has_preorder":false,"cover_landscape_image":{"uri":""},"cover_portrait_image":{"uri":""},"cover_square_image":{"uri":""},"screenshots":[],"supportedBinaries":{"count":0,"edges":[]}},"__isAppBinary":"","__isAppBinaryWithFileAsset":"","version_code":5,"versionCode":5,"created_date":1473687833,"binary_release_channels":{"count":0,"nodes":[{"id":"1700850070180525","channel_name":"LIVE","latest_supported_binary":{"id":"","version":"","platform":"","file_name":"","uri":"","change_log":"","changeLog":"","richChangeLog":"","binary_application":{"primary_binaries":{"count":0,"edges":[]},"id":"","platform":"","display_name":"","displayName":"","release_channels":{"count":0,"nodes":[]},"revisions":{"count":0,"nodes":[]},"organization":{"id":"","is_authorized_for_quest":false},"is_concept":false,"is_approved":false,"is_enterprise_enabled":false,"canonicalName":"","release_date":0,"viewer_has_preorder":false,"cover_landscape_image":{"uri":""},"cover_portrait_image":{"uri":""},"cover_square_image":{"uri":""},"screenshots":[],"supportedBinaries":{"count":0,"edges":[]}},"__isAppBinary":"","__isAppBinaryWithFileAsset":"","version_code":0,"versionCode":0,"created_date":0,"binary_release_channels":null,"__typename":""}}]},"__typename":"AndroidBinary"}},{"node":{"id":"1244757438891691","version":"1.0","platform":"","file_name":"Magne01.apk","uri":"","change_log":"","changeLog":"","richChangeLog":"","binary_application":{"primary_binaries":{"count":0,"edges":[]},"id":"","platform":"","display_name":"","displayName":"","release_channels":{"count":0,"nodes":[]},"revisions":{"count":0,"nodes":[]},"organization":{"id":"","is_authorized_for_quest":false},"is_concept":false,"is_approved":false,"is_enterprise_enabled":false,"canonicalName":"","release_date":0,"viewer_has_preorder":false,"cover_landscape_image":{"uri":""},"cover_portrait_image":{"uri":""},"cover_square_image":{"uri":""},"screenshots":[],"supportedBinaries":{"count":0,"edges":[]}},"__isAppBinary":"","__isAppBinaryWithFileAsset":"","version_code":4,"versionCode":4,"created_date":1472029854,"binary_release_channels":{"count":0,"nodes":[{"id":"1700850070180525","channel_name":"LIVE","latest_supported_binary":{"id":"","version":"","platform":"","file_name":"","uri":"","change_log":"","changeLog":"","richChangeLog":"","binary_application":{"primary_binaries":{"count":0,"edges":[]},"id":"","platform":"","display_name":"","displayName":"","release_channels":{"count":0,"nodes":[]},"revisions":{"count":0,"nodes":[]},"organization":{"id":"","is_authorized_for_quest":false},"is_concept":false,"is_approved":false,"is_enterprise_enabled":false,"canonicalName":"","release_date":0,"viewer_has_preorder":false,"cover_landscape_image":{"uri":""},"cover_portrait_image":{"uri":""},"cover_square_image":{"uri":""},"screenshots":[],"supportedBinaries":{"count":0,"edges":[]}},"__isAppBinary":"","__isAppBinaryWithFileAsset":"","version_code":0,"versionCode":0,"created_date":0,"binary_release_channels":null,"__typename":""}}]},"__typename":"AndroidBinary"}},{"node":{"id":"1238778379489597","version":"1.0","platform":"","file_name":"Magne01.apk","uri":"","change_log":"","changeLog":"","richChangeLog":"","binary_application":{"primary_binaries":{"count":0,"edges":[]},"id":"","platform":"","display_name":"","displayName":"","release_channels":{"count":0,"nodes":[]},"revisions":{"count":0,"nodes":[]},"organization":{"id":"","is_authorized_for_quest":false},"is_concept":false,"is_approved":false,"is_enterprise_enabled":false,"canonicalName":"","release_date":0,"viewer_has_preorder":false,"cover_landscape_image":{"uri":""},"cover_portrait_image":{"uri":""},"cover_square_image":{"uri":""},"screenshots":[],"supportedBinaries":{"count":0,"edges":[]}},"__isAppBinary":"","__isAppBinaryWithFileAsset":"","version_code":3,"versionCode":3,"created_date":1471443623,"binary_release_channels":{"count":0,"nodes":[{"id":"1700850070180525","channel_name":"LIVE","latest_supported_binary":{"id":"","version":"","platform":"","file_name":"","uri":"","change_log":"","changeLog":"","richChangeLog":"","binary_application":{"primary_binaries":{"count":0,"edges":[]},"id":"","platform":"","display_name":"","displayName":"","release_channels":{"count":0,"nodes":[]},"revisions":{"count":0,"nodes":[]},"organization":{"id":"","is_authorized_for_quest":false},"is_concept":false,"is_approved":false,"is_enterprise_enabled":false,"canonicalName":"","release_date":0,"viewer_has_preorder":false,"cover_landscape_image":{"uri":""},"cover_portrait_image":{"uri":""},"cover_square_image":{"uri":""},"screenshots":[],"supportedBinaries":{"count":0,"edges":[]}},"__isAppBinary":"","__isAppBinaryWithFileAsset":"","version_code":0,"versionCode":0,"created_date":0,"binary_release_channels":null,"__typename":""}}]},"__typename":"AndroidBinary"}},{"node":{"id":"1206605639373538","version":"1.0","platform":"","file_name":"Magne01.apk","uri":"","change_log":"","changeLog":"","richChangeLog":"","binary_application":{"primary_binaries":{"count":0,"edges":[]},"id":"","platform":"","display_name":"","displayName":"","release_channels":{"count":0,"nodes":[]},"revisions":{"count":0,"nodes":[]},"organization":{"id":"","is_authorized_for_quest":false},"is_concept":false,"is_approved":false,"is_enterprise_enabled":false,"canonicalName":"","release_date":0,"viewer_has_preorder":false,"cover_landscape_image":{"uri":""},"cover_portrait_image":{"uri":""},"cover_square_image":{"uri":""},"screenshots":[],"supportedBinaries":{"count":0,"edges":[]}},"__isAppBinary":"","__isAppBinaryWithFileAsset":"","version_code":2,"versionCode":2,"created_date":1467661351,"binary_release_channels":{"count":0,"nodes":[{"id":"1700850070180525","channel_name":"LIVE","latest_supported_binary":{"id":"","version":"","platform":"","file_name":"","uri":"","change_log":"","changeLog":"","richChangeLog":"","binary_application":{"primary_binaries":{"count":0,"edges":[]},"id":"","platform":"","display_name":"","displayName":"","release_channels":{"count":0,"nodes":[]},"revisions":{"count":0,"nodes":[]},"organization":{"id":"","is_authorized_for_quest":false},"is_concept":false,"is_approved":false,"is_enterprise_enabled":false,"canonicalName":"","release_date":0,"viewer_has_preorder":false,"cover_landscape_image":{"uri":""},"cover_portrait_image":{"uri":""},"cover_square_image":{"uri":""},"screenshots":[],"supportedBinaries":{"count":0,"edges":[]}},"__isAppBinary":"","__isAppBinaryWithFileAsset":"","version_code":0,"versionCode":0,"created_date":0,"binary_release_channels":null,"__typename":""}}]},"__typename":"AndroidBinary"}},{"node":{"id":"1025885774154906","version":"1.0","platform":"","file_name":"Magnetique01.apk","uri":"","change_log":"","changeLog":"","richChangeLog":"","binary_application":{"primary_binaries":{"count":0,"edges":[]},"id":"","platform":"","display_name":"","displayName":"","release_channels":{"count":0,"nodes":[]},"revisions":{"count":0,"nodes":[]},"organization":{"id":"","is_authorized_for_quest":false},"is_concept":false,"is_approved":false,"is_enterprise_enabled":false,"canonicalName":"","release_date":0,"viewer_has_preorder":false,"cover_landscape_image":{"uri":""},"cover_portrait_image":{"uri":""},"cover_square_image":{"uri":""},"screenshots":[],"supportedBinaries":{"count":0,"edges":[]}},"__isAppBinary":"","__isAppBinaryWithFileAsset":"","version_code":1,"versionCode":1,"created_date":1465821895,"binary_release_channels":{"count":0,"nodes":[{"id":"1700850070180525","channel_name":"LIVE","latest_supported_binary":{"id":"","version":"","platform":"","file_name":"","uri":"","change_log":"","changeLog":"","richChangeLog":"","binary_application":{"primary_binaries":{"count":0,"edges":[]},"id":"","platform":"","display_name":"","displayName":"","release_channels":{"count":0,"nodes":[]},"revisions":{"count":0,"nodes":[]},"organization":{"id":"","is_authorized_for_quest":false},"is_concept":false,"is_approved":false,"is_enterprise_enabled":false,"canonicalName":"","release_date":0,"viewer_has_preorder":false,"cover_landscape_image":{"uri":""},"cover_portrait_image":{"uri":""},"cover_square_image":{"uri":""},"screenshots":[],"supportedBinaries":{"count":0,"edges":[]}},"__isAppBinary":"","__isAppBinaryWithFileAsset":"","version_code":0,"versionCode":0,"created_date":0,"binary_release_channels":null,"__typename":""}}]},"__typename":"AndroidBinary"}}]},"latest_supported_binary":{"binary_application":{"display_name":""}},"appName":"Magnetique - VR Comic","headset":"GEARVR","squareImage":"https://scontent.oculuscdn.com/v/t64.5771-25/12728016_665149956967680_261246238_n.jpg?stp=dst-jpg_q92_s720x720\u0026_nc_cat=100\u0026ccb=1-5\u0026_nc_sid=79b88e\u0026_nc_ohc=efd3Q26FVkkAX9YxYbY\u0026_nc_ht=scontent.oculuscdn.com\u0026oh=00_AT_bTcCfWgihEwDsER9vmeQ9n0gFIOJeMVYZxStHg0N6ig\u0026oe=621736DF","id":"1174459059254863"}}}