{"data":{"node":{"binaries":{"edges":[{"node":{"change_log":"N/A","id":"1821972751239697","version":"1","version_code":974,"created_date":1564794481}},{"node":{"change_log":"N/A","id":"1805924062844566","version":"1","version_code":969,"created_date":1563917486}},{"node":{"change_log":"N/A","id":"1762855120484794","version":"1","version_code":957,"created_date":1561596211}},{"node":{"change_log":"N/A","id":"1715082681928705","version":"1","version_code":939,"created_date":1559069119}},{"node":{"change_log":"N/A","id":"1714959888607651","version":"1","version_code":937,"created_date":1559062787}},{"node":{"change_log":"N/A","id":"1709716495798657","version":"1","version_code":935,"created_date":1558763915}},{"node":{"change_log":"N/A","id":"1709396072497366","version":"1","version_code":933,"created_date":1558743247}},{"node":{"change_log":"N/A","id":"1707929809310659","version":"1","version_code":931,"created_date":1558657613}},{"node":{"change_log":"N/A","id":"1706949806075326","version":"1","version_code":930,"created_date":1558604481}},{"node":{"change_log":"N/A","id":"1705041179599522","version":"1","version_code":927,"created_date":1558488623}},{"node":{"change_log":"N/A","id":"1682797715157202","version":"1","version_code":912,"created_date":1557191701}}]},"latest_supported_binary":{"binary_application":{"display_name":""}},"appName":"Fujii","headset":"RIFT","squareImage":"https://scontent.oculuscdn.com/v/t64.5771-25/q92/s720x720/75295894_256007348842078_8327689502428495872_n.jpg?_nc_cat=110\u0026ccb=1-5\u0026_nc_sid=79b88e\u0026_nc_ohc=0n2Ywaeij3wAX9lYWSm\u0026_nc_ht=scontent.oculuscdn.com\u0026oh=1f77cc1758db32bbb030f5a42a7e2258\u0026oe=612C9F15","id":"1237907126312932"}}}