{"data":{"node":{"binaries":{"edges":[{"node":{"change_log":"N/A","id":"1650249981740040","version":"2.3.1.0","version_code":37,"created_date":1525207586}},{"node":{"change_log":"N/A","id":"1615681355196903","version":"2.3.0.0","version_code":36,"created_date":1522271231}},{"node":{"change_log":"N/A","id":"1536048539826852","version":"2.1.3.1","version_code":35,"created_date":1515613311}},{"node":{"change_log":"N/A","id":"1534077550023951","version":"2.1.2.1","version_code":34,"created_date":1515442673}},{"node":{"change_log":"N/A","id":"1527564004008639","version":"2.1.1.4","version_code":33,"created_date":1514939109}},{"node":{"change_log":"N/A","id":"1509637999134573","version":"2.1.0.2","version_code":29,"created_date":1513293339}},{"node":{"change_log":"N/A","id":"1500638376701202","version":"2.0.1.3","version_code":27,"created_date":1512502132}}]},"latest_supported_binary":{"binary_application":{"display_name":""}},"appName":"Just In Time Incorporated","headset":"RIFT","squareImage":"https://scontent.oculuscdn.com/v/t64.5771-25/q92/s720x720/12410200_1866226906735170_6170804699298529280_n.jpg?_nc_cat=104\u0026ccb=1-3\u0026_nc_sid=79b88e\u0026_nc_ohc=z5ud8mELMIAAX-e4PKY\u0026_nc_ht=scontent.oculuscdn.com\u0026oh=be5af8d22e0d06dcb9f9c21304595be8\u0026oe=60FBA610","id":"1429983913766649"}}}