{"data":{"node":{"binaries":{"edges":[{"node":{"id":"2980659748714060","version":"1.00.7","platform":"","file_name":"jwb_production_normal_GearVR_1.00.7-328.apk","uri":"","change_log":"","changeLog":"","richChangeLog":"","binary_application":{"primary_binaries":{"count":0,"edges":[]},"id":"","platform":"","display_name":"","displayName":"","release_channels":{"count":0,"nodes":[]},"revisions":{"count":0,"nodes":[]},"organization":{"id":"","is_authorized_for_quest":false},"is_concept":false,"is_approved":false,"is_enterprise_enabled":false,"canonicalName":"","release_date":0,"viewer_has_preorder":false,"cover_landscape_image":{"uri":""},"cover_portrait_image":{"uri":""},"cover_square_image":{"uri":""},"screenshots":[],"supportedBinaries":{"count":0,"edges":[]}},"__isAppBinary":"","__isAppBinaryWithFileAsset":"","version_code":1000007,"versionCode":1000007,"created_date":1591721643,"binary_release_channels":{"count":0,"nodes":[{"id":"463787197357930","channel_name":"LIVE","latest_supported_binary":{"id":"","version":"","platform":"","file_name":"","uri":"","change_log":"","changeLog":"","richChangeLog":"","binary_application":{"primary_binaries":{"count":0,"edges":[]},"id":"","platform":"","display_name":"","displayName":"","release_channels":{"count":0,"nodes":[]},"revisions":{"count":0,"nodes":[]},"organization":{"id":"","is_authorized_for_quest":false},"is_concept":false,"is_approved":false,"is_enterprise_enabled":false,"canonicalName":"","release_date":0,"viewer_has_preorder":false,"cover_landscape_image":{"uri":""},"cover_portrait_image":{"uri":""},"cover_square_image":{"uri":""},"screenshots":[],"supportedBinaries":{"count":0,"edges":[]}},"__isAppBinary":"","__isAppBinaryWithFileAsset":"","version_code":0,"versionCode":0,"created_date":0,"binary_release_channels":null,"__typename":""}}]},"__typename":"AndroidBinary"}},{"node":{"id":"1811184325661614","version":"1.00.5","platform":"","file_name":"jwb_production_normal_GearVr.apk","uri":"","change_log":"","changeLog":"","richChangeLog":"","binary_application":{"primary_binaries":{"count":0,"edges":[]},"id":"","platform":"","display_name":"","displayName":"","release_channels":{"count":0,"nodes":[]},"revisions":{"count":0,"nodes":[]},"organization":{"id":"","is_authorized_for_quest":false},"is_concept":false,"is_approved":false,"is_enterprise_enabled":false,"canonicalName":"","release_date":0,"viewer_has_preorder":false,"cover_landscape_image":{"uri":""},"cover_portrait_image":{"uri":""},"cover_square_image":{"uri":""},"screenshots":[],"supportedBinaries":{"count":0,"edges":[]}},"__isAppBinary":"","__isAppBinaryWithFileAsset":"","version_code":1000005,"versionCode":1000005,"created_date":1535385362,"binary_release_channels":{"count":0,"nodes":[{"id":"463787197357930","channel_name":"LIVE","latest_supported_binary":{"id":"","version":"","platform":"","file_name":"","uri":"","change_log":"","changeLog":"","richChangeLog":"","binary_application":{"primary_binaries":{"count":0,"edges":[]},"id":"","platform":"","display_name":"","displayName":"","release_channels":{"count":0,"nodes":[]},"revisions":{"count":0,"nodes":[]},"organization":{"id":"","is_authorized_for_quest":false},"is_concept":false,"is_approved":false,"is_enterprise_enabled":false,"canonicalName":"","release_date":0,"viewer_has_preorder":false,"cover_landscape_image":{"uri":""},"cover_portrait_image":{"uri":""},"cover_square_image":{"uri":""},"screenshots":[],"supportedBinaries":{"count":0,"edges":[]}},"__isAppBinary":"","__isAppBinaryWithFileAsset":"","version_code":0,"versionCode":0,"created_date":0,"binary_release_channels":null,"__typename":""}}]},"__typename":"AndroidBinary"}},{"node":{"id":"1807429696037077","version":"1.00.4","platform":"","file_name":"jwb_production_normal_GearVr.apk","uri":"","change_log":"","changeLog":"","richChangeLog":"","binary_application":{"primary_binaries":{"count":0,"edges":[]},"id":"","platform":"","display_name":"","displayName":"","release_channels":{"count":0,"nodes":[]},"revisions":{"count":0,"nodes":[]},"organization":{"id":"","is_authorized_for_quest":false},"is_concept":false,"is_approved":false,"is_enterprise_enabled":false,"canonicalName":"","release_date":0,"viewer_has_preorder":false,"cover_landscape_image":{"uri":""},"cover_portrait_image":{"uri":""},"cover_square_image":{"uri":""},"screenshots":[],"supportedBinaries":{"count":0,"edges":[]}},"__isAppBinary":"","__isAppBinaryWithFileAsset":"","version_code":1000004,"versionCode":1000004,"created_date":1535136654,"binary_release_channels":{"count":0,"nodes":[{"id":"463787197357930","channel_name":"LIVE","latest_supported_binary":{"id":"","version":"","platform":"","file_name":"","uri":"","change_log":"","changeLog":"","richChangeLog":"","binary_application":{"primary_binaries":{"count":0,"edges":[]},"id":"","platform":"","display_name":"","displayName":"","release_channels":{"count":0,"nodes":[]},"revisions":{"count":0,"nodes":[]},"organization":{"id":"","is_authorized_for_quest":false},"is_concept":false,"is_approved":false,"is_enterprise_enabled":false,"canonicalName":"","release_date":0,"viewer_has_preorder":false,"cover_landscape_image":{"uri":""},"cover_portrait_image":{"uri":""},"cover_square_image":{"uri":""},"screenshots":[],"supportedBinaries":{"count":0,"edges":[]}},"__isAppBinary":"","__isAppBinaryWithFileAsset":"","version_code":0,"versionCode":0,"created_date":0,"binary_release_channels":null,"__typename":""}}]},"__typename":"AndroidBinary"}},{"node":{"id":"1682475321865849","version":"1.00.1","platform":"","file_name":"jwb_production_normal_GearVr.apk","uri":"","change_log":"","changeLog":"","richChangeLog":"","binary_application":{"primary_binaries":{"count":0,"edges":[]},"id":"","platform":"","display_name":"","displayName":"","release_channels":{"count":0,"nodes":[]},"revisions":{"count":0,"nodes":[]},"organization":{"id":"","is_authorized_for_quest":false},"is_concept":false,"is_approved":false,"is_enterprise_enabled":false,"canonicalName":"","release_date":0,"viewer_has_preorder":false,"cover_landscape_image":{"uri":""},"cover_portrait_image":{"uri":""},"cover_square_image":{"uri":""},"screenshots":[],"supportedBinaries":{"count":0,"edges":[]}},"__isAppBinary":"","__isAppBinaryWithFileAsset":"","version_code":1000001,"versionCode":1000001,"created_date":1528308481,"binary_release_channels":{"count":0,"nodes":[{"id":"463787197357930","channel_name":"LIVE","latest_supported_binary":{"id":"","version":"","platform":"","file_name":"","uri":"","change_log":"","changeLog":"","richChangeLog":"","binary_application":{"primary_binaries":{"count":0,"edges":[]},"id":"","platform":"","display_name":"","displayName":"","release_channels":{"count":0,"nodes":[]},"revisions":{"count":0,"nodes":[]},"organization":{"id":"","is_authorized_for_quest":false},"is_concept":false,"is_approved":false,"is_enterprise_enabled":false,"canonicalName":"","release_date":0,"viewer_has_preorder":false,"cover_landscape_image":{"uri":""},"cover_portrait_image":{"uri":""},"cover_square_image":{"uri":""},"screenshots":[],"supportedBinaries":{"count":0,"edges":[]}},"__isAppBinary":"","__isAppBinaryWithFileAsset":"","version_code":0,"versionCode":0,"created_date":0,"binary_release_channels":null,"__typename":""}}]},"__typename":"AndroidBinary"}},{"node":{"id":"1642398465873535","version":"0.99.19","platform":"","file_name":"jwb_production_normal_GearVr.apk","uri":"","change_log":"","changeLog":"","richChangeLog":"","binary_application":{"primary_binaries":{"count":0,"edges":[]},"id":"","platform":"","display_name":"","displayName":"","release_channels":{"count":0,"nodes":[]},"revisions":{"count":0,"nodes":[]},"organization":{"id":"","is_authorized_for_quest":false},"is_concept":false,"is_approved":false,"is_enterprise_enabled":false,"canonicalName":"","release_date":0,"viewer_has_preorder":false,"cover_landscape_image":{"uri":""},"cover_portrait_image":{"uri":""},"cover_square_image":{"uri":""},"screenshots":[],"supportedBinaries":{"count":0,"edges":[]}},"__isAppBinary":"","__isAppBinaryWithFileAsset":"","version_code":99019,"versionCode":99019,"created_date":1524870181,"binary_release_channels":{"count":0,"nodes":[{"id":"463787197357930","channel_name":"LIVE","latest_supported_binary":{"id":"","version":"","platform":"","file_name":"","uri":"","change_log":"","changeLog":"","richChangeLog":"","binary_application":{"primary_binaries":{"count":0,"edges":[]},"id":"","platform":"","display_name":"","displayName":"","release_channels":{"count":0,"nodes":[]},"revisions":{"count":0,"nodes":[]},"organization":{"id":"","is_authorized_for_quest":false},"is_concept":false,"is_approved":false,"is_enterprise_enabled":false,"canonicalName":"","release_date":0,"viewer_has_preorder":false,"cover_landscape_image":{"uri":""},"cover_portrait_image":{"uri":""},"cover_square_image":{"uri":""},"screenshots":[],"supportedBinaries":{"count":0,"edges":[]}},"__isAppBinary":"","__isAppBinaryWithFileAsset":"","version_code":0,"versionCode":0,"created_date":0,"binary_release_channels":null,"__typename":""}}]},"__typename":"AndroidBinary"}},{"node":{"id":"1641042646009117","version":"0.99.17","platform":"","file_name":"jwb_production_normal_GearVr.apk","uri":"","change_log":"","changeLog":"","richChangeLog":"","binary_application":{"primary_binaries":{"count":0,"edges":[]},"id":"","platform":"","display_name":"","displayName":"","release_channels":{"count":0,"nodes":[]},"revisions":{"count":0,"nodes":[]},"organization":{"id":"","is_authorized_for_quest":false},"is_concept":false,"is_approved":false,"is_enterprise_enabled":false,"canonicalName":"","release_date":0,"viewer_has_preorder":false,"cover_landscape_image":{"uri":""},"cover_portrait_image":{"uri":""},"cover_square_image":{"uri":""},"screenshots":[],"supportedBinaries":{"count":0,"edges":[]}},"__isAppBinary":"","__isAppBinaryWithFileAsset":"","version_code":99017,"versionCode":99017,"created_date":1524753084,"binary_release_channels":{"count":0,"nodes":[{"id":"463787197357930","channel_name":"LIVE","latest_supported_binary":{"id":"","version":"","platform":"","file_name":"","uri":"","change_log":"","changeLog":"","richChangeLog":"","binary_application":{"primary_binaries":{"count":0,"edges":[]},"id":"","platform":"","display_name":"","displayName":"","release_channels":{"count":0,"nodes":[]},"revisions":{"count":0,"nodes":[]},"organization":{"id":"","is_authorized_for_quest":false},"is_concept":false,"is_approved":false,"is_enterprise_enabled":false,"canonicalName":"","release_date":0,"viewer_has_preorder":false,"cover_landscape_image":{"uri":""},"cover_portrait_image":{"uri":""},"cover_square_image":{"uri":""},"screenshots":[],"supportedBinaries":{"count":0,"edges":[]}},"__isAppBinary":"","__isAppBinaryWithFileAsset":"","version_code":0,"versionCode":0,"created_date":0,"binary_release_channels":null,"__typename":""}}]},"__typename":"AndroidBinary"}},{"node":{"id":"1639505512829497","version":"0.99.16 Oculus Go","platform":"","file_name":"jwb_production_normal_GearVr.apk","uri":"","change_log":"","changeLog":"","richChangeLog":"","binary_application":{"primary_binaries":{"count":0,"edges":[]},"id":"","platform":"","display_name":"","displayName":"","release_channels":{"count":0,"nodes":[]},"revisions":{"count":0,"nodes":[]},"organization":{"id":"","is_authorized_for_quest":false},"is_concept":false,"is_approved":false,"is_enterprise_enabled":false,"canonicalName":"","release_date":0,"viewer_has_preorder":false,"cover_landscape_image":{"uri":""},"cover_portrait_image":{"uri":""},"cover_square_image":{"uri":""},"screenshots":[],"supportedBinaries":{"count":0,"edges":[]}},"__isAppBinary":"","__isAppBinaryWithFileAsset":"","version_code":99016,"versionCode":99016,"created_date":1524615827,"binary_release_channels":{"count":0,"nodes":[{"id":"463787197357930","channel_name":"LIVE","latest_supported_binary":{"id":"","version":"","platform":"","file_name":"","uri":"","change_log":"","changeLog":"","richChangeLog":"","binary_application":{"primary_binaries":{"count":0,"edges":[]},"id":"","platform":"","display_name":"","displayName":"","release_channels":{"count":0,"nodes":[]},"revisions":{"count":0,"nodes":[]},"organization":{"id":"","is_authorized_for_quest":false},"is_concept":false,"is_approved":false,"is_enterprise_enabled":false,"canonicalName":"","release_date":0,"viewer_has_preorder":false,"cover_landscape_image":{"uri":""},"cover_portrait_image":{"uri":""},"cover_square_image":{"uri":""},"screenshots":[],"supportedBinaries":{"count":0,"edges":[]}},"__isAppBinary":"","__isAppBinaryWithFileAsset":"","version_code":0,"versionCode":0,"created_date":0,"binary_release_channels":null,"__typename":""}}]},"__typename":"AndroidBinary"}},{"node":{"id":"1635477099899005","version":"0.99.13 Oculus Go","platform":"","file_name":"jwb_production_normal_GearVr.apk","uri":"","change_log":"","changeLog":"","richChangeLog":"","binary_application":{"primary_binaries":{"count":0,"edges":[]},"id":"","platform":"","display_name":"","displayName":"","release_channels":{"count":0,"nodes":[]},"revisions":{"count":0,"nodes":[]},"organization":{"id":"","is_authorized_for_quest":false},"is_concept":false,"is_approved":false,"is_enterprise_enabled":false,"canonicalName":"","release_date":0,"viewer_has_preorder":false,"cover_landscape_image":{"uri":""},"cover_portrait_image":{"uri":""},"cover_square_image":{"uri":""},"screenshots":[],"supportedBinaries":{"count":0,"edges":[]}},"__isAppBinary":"","__isAppBinaryWithFileAsset":"","version_code":99013,"versionCode":99013,"created_date":1524253836,"binary_release_channels":{"count":0,"nodes":[{"id":"463787197357930","channel_name":"LIVE","latest_supported_binary":{"id":"","version":"","platform":"","file_name":"","uri":"","change_log":"","changeLog":"","richChangeLog":"","binary_application":{"primary_binaries":{"count":0,"edges":[]},"id":"","platform":"","display_name":"","displayName":"","release_channels":{"count":0,"nodes":[]},"revisions":{"count":0,"nodes":[]},"organization":{"id":"","is_authorized_for_quest":false},"is_concept":false,"is_approved":false,"is_enterprise_enabled":false,"canonicalName":"","release_date":0,"viewer_has_preorder":false,"cover_landscape_image":{"uri":""},"cover_portrait_image":{"uri":""},"cover_square_image":{"uri":""},"screenshots":[],"supportedBinaries":{"count":0,"edges":[]}},"__isAppBinary":"","__isAppBinaryWithFileAsset":"","version_code":0,"versionCode":0,"created_date":0,"binary_release_channels":null,"__typename":""}}]},"__typename":"AndroidBinary"}}]},"latest_supported_binary":{"binary_application":{"display_name":""}},"appName":"Jurassic World: Blue","headset":"GEARVR","squareImage":"https://scontent.oculuscdn.com/v/t64.5771-25/q92/s720x720/38974541_240193366639231_5064756711118602240_n.jpg?_nc_cat=102\u0026ccb=1-5\u0026_nc_sid=79b88e\u0026_nc_ohc=GW2bD2Wjo_IAX9-93x-\u0026_nc_ht=scontent.oculuscdn.com\u0026oh=00_AT8pmlOEflZa4f4gqijpQjCQfUyzwVD6FOggqFW-AyRZAQ\u0026oe=6216AEE0","id":"1599089200204462"}}}