{"data":{"node":{"binaries":{"edges":[{"node":{"change_log":"N/A","id":"3831166936952373","version":"1.5.5","version_code":48,"created_date":1619907430}},{"node":{"change_log":"N/A","id":"3820612634674470","version":"1.5.4","version_code":47,"created_date":1619579277}},{"node":{"change_log":"N/A","id":"3784434278292306","version":"1.5.2","version_code":45,"created_date":1618457224}},{"node":{"change_log":"N/A","id":"3458062644262806","version":"1.3","version_code":44,"created_date":1608003558}},{"node":{"change_log":"N/A","id":"2967644916637917","version":"1.2.1","version_code":38,"created_date":1592798309}},{"node":{"change_log":"N/A","id":"2903882723014137","version":"1.2","version_code":33,"created_date":1590643249}},{"node":{"change_log":"N/A","id":"2759538327448578","version":"1.1","version_code":27,"created_date":1585167497}},{"node":{"change_log":"N/A","id":"2731894666879611","version":"1.05","version_code":23,"created_date":1584073970}},{"node":{"change_log":"N/A","id":"2730127427056335","version":"1.05","version_code":22,"created_date":1584001709}},{"node":{"change_log":"N/A","id":"2727522973983447","version":"1.05","version_code":21,"created_date":1583889668}},{"node":{"change_log":"N/A","id":"2725797204156024","version":"1.05","version_code":20,"created_date":1583819741}},{"node":{"change_log":"N/A","id":"2719289144806830","version":"1.05","version_code":18,"created_date":1583548020}},{"node":{"change_log":"N/A","id":"2713226632079748","version":"1.05","version_code":17,"created_date":1583291897}},{"node":{"change_log":"N/A","id":"2711239932278418","version":"1.05","version_code":16,"created_date":1583207358}},{"node":{"change_log":"N/A","id":"2703076509761427","version":"1.05","version_code":15,"created_date":1582865392}},{"node":{"change_log":"N/A","id":"2700940553308356","version":"1.05","version_code":13,"created_date":1582772442}},{"node":{"change_log":"N/A","id":"2437384012997346","version":"1.03","version_code":4,"created_date":1571862990}},{"node":{"change_log":"N/A","id":"2435572776511803","version":"1.02","version_code":3,"created_date":1571786858}},{"node":{"change_log":"N/A","id":"2435565116512569","version":"1.02","version_code":2,"created_date":1571786501}},{"node":{"change_log":"N/A","id":"2433333090069105","version":"1.0","version_code":1,"created_date":1571695021}}]},"latest_supported_binary":{"binary_application":{"display_name":""}},"appName":"Color Space","headset":"RIFT","squareImage":"https://scontent.oculuscdn.com/v/t64.5771-25/q92/s720x720/38974809_450640602833957_213186101524211599_n.jpg?_nc_cat=109\u0026ccb=1-3\u0026_nc_sid=79b88e\u0026_nc_ohc=DSqwyFTw1Z0AX_q8neP\u0026_nc_ht=scontent.oculuscdn.com\u0026oh=c2a1e04c4d9a6e3838e13eccde64bb1b\u0026oe=6104A1CE","id":"2433318586737222"}}}