{"data":{"node":{"binaries":{"edges":[{"node":{"change_log":"N/A","id":"3502212439820350","version":"1","version_code":315,"created_date":1583490994}},{"node":{"change_log":"N/A","id":"3222505657791031","version":"0.7","version_code":240,"created_date":1575646058}}]},"latest_supported_binary":{"binary_application":{"display_name":""}},"appName":"Let\u0027s Create! Pottery VR","headset":"RIFT","squareImage":"https://scontent.oculuscdn.com/v/t64.5771-25/q92/s720x720/38974883_404707686981832_3713869671234011136_n.jpg?_nc_cat=105\u0026ccb=1-3\u0026_nc_sid=79b88e\u0026_nc_ohc=dvJb6udtKUQAX8fw8De\u0026_nc_ht=scontent.oculuscdn.com\u0026oh=96a0fc0f4b1b2d74394cd88f823e745b\u0026oe=610457C5","id":"2503391089702495"}}}