{"data":{"node":{"binaries":{"edges":[{"node":{"change_log":"N/A","id":"2839194359430692","version":"FREEDIVER Version 1.04","version_code":85,"created_date":1560369781}},{"node":{"change_log":"N/A","id":"2812467932103335","version":"FREEDIVER Version 1.03","version_code":76,"created_date":1559235016}},{"node":{"change_log":"N/A","id":"2787852337898228","version":"51926","version_code":67,"created_date":1558147679}},{"node":{"change_log":"N/A","id":"2770749649608497","version":"51682 --notes InternalQA","version_code":49,"created_date":1557357725}},{"node":{"change_log":"N/A","id":"2759804314036364","version":"51585","version_code":40,"created_date":1556833328}}]},"latest_supported_binary":{"binary_application":{"display_name":""}},"appName":"FREEDIVER: Triton Down","headset":"RIFT","squareImage":"https://scontent.oculuscdn.com/v/t64.5771-25/q92/s720x720/38974643_395329214641582_3445387503169699840_n.jpg?_nc_cat=102\u0026ccb=1-5\u0026_nc_sid=79b88e\u0026_nc_ohc=tRoepsmJ5EoAX-GsEPC\u0026_nc_ht=scontent.oculuscdn.com\u0026oh=6d2782f07dcb758b25119e1bd4feada7\u0026oe=61337158","id":"2683634734986656"}}}