{"data":{"node":{"binaries":{"edges":[{"node":{"id":"7125359357535875","version":"9.0.77238","platform":"","file_name":"oculus-prod-sling-armeabi-v7a-release-9.0.77238.2.apk","uri":"","change_log":"","changeLog":"","richChangeLog":"","binary_application":{"primary_binaries":{"count":0,"edges":[]},"id":"","platform":"","display_name":"","displayName":"","release_channels":{"count":0,"nodes":[]},"revisions":{"count":0,"nodes":[]},"organization":{"id":"","is_authorized_for_quest":false},"is_concept":false,"is_approved":false,"is_enterprise_enabled":false,"canonicalName":"","release_date":0,"viewer_has_preorder":false,"cover_landscape_image":{"uri":""},"cover_portrait_image":{"uri":""},"cover_square_image":{"uri":""},"screenshots":[],"supportedBinaries":{"count":0,"edges":[]}},"__isAppBinary":"","__isAppBinaryWithFileAsset":"","version_code":90772380,"versionCode":90772380,"created_date":1642721854,"binary_release_channels":{"count":0,"nodes":[{"id":"563338427502637","channel_name":"LIVE","latest_supported_binary":{"id":"","version":"","platform":"","file_name":"","uri":"","change_log":"","changeLog":"","richChangeLog":"","binary_application":{"primary_binaries":{"count":0,"edges":[]},"id":"","platform":"","display_name":"","displayName":"","release_channels":{"count":0,"nodes":[]},"revisions":{"count":0,"nodes":[]},"organization":{"id":"","is_authorized_for_quest":false},"is_concept":false,"is_approved":false,"is_enterprise_enabled":false,"canonicalName":"","release_date":0,"viewer_has_preorder":false,"cover_landscape_image":{"uri":""},"cover_portrait_image":{"uri":""},"cover_square_image":{"uri":""},"screenshots":[],"supportedBinaries":{"count":0,"edges":[]}},"__isAppBinary":"","__isAppBinaryWithFileAsset":"","version_code":0,"versionCode":0,"created_date":0,"binary_release_channels":null,"__typename":""}}]},"__typename":"AndroidBinary"}},{"node":{"id":"6440601972678287","version":"7.3.99","platform":"","file_name":"oculus-prod-sling-armeabi-v7a-release-7.3.99.apk","uri":"","change_log":"","changeLog":"","richChangeLog":"","binary_application":{"primary_binaries":{"count":0,"edges":[]},"id":"","platform":"","display_name":"","displayName":"","release_channels":{"count":0,"nodes":[]},"revisions":{"count":0,"nodes":[]},"organization":{"id":"","is_authorized_for_quest":false},"is_concept":false,"is_approved":false,"is_enterprise_enabled":false,"canonicalName":"","release_date":0,"viewer_has_preorder":false,"cover_landscape_image":{"uri":""},"cover_portrait_image":{"uri":""},"cover_square_image":{"uri":""},"screenshots":[],"supportedBinaries":{"count":0,"edges":[]}},"__isAppBinary":"","__isAppBinaryWithFileAsset":"","version_code":70300990,"versionCode":70300990,"created_date":1632795082,"binary_release_channels":{"count":0,"nodes":[{"id":"563338427502637","channel_name":"LIVE","latest_supported_binary":{"id":"","version":"","platform":"","file_name":"","uri":"","change_log":"","changeLog":"","richChangeLog":"","binary_application":{"primary_binaries":{"count":0,"edges":[]},"id":"","platform":"","display_name":"","displayName":"","release_channels":{"count":0,"nodes":[]},"revisions":{"count":0,"nodes":[]},"organization":{"id":"","is_authorized_for_quest":false},"is_concept":false,"is_approved":false,"is_enterprise_enabled":false,"canonicalName":"","release_date":0,"viewer_has_preorder":false,"cover_landscape_image":{"uri":""},"cover_portrait_image":{"uri":""},"cover_square_image":{"uri":""},"screenshots":[],"supportedBinaries":{"count":0,"edges":[]}},"__isAppBinary":"","__isAppBinaryWithFileAsset":"","version_code":0,"versionCode":0,"created_date":0,"binary_release_channels":null,"__typename":""}}]},"__typename":"AndroidBinary"}},{"node":{"id":"5461120243959803","version":"7.3.97","platform":"","file_name":"oculus-prod-sling-armeabi-v7a-release-7.3.97-Quest.apk","uri":"","change_log":"","changeLog":"","richChangeLog":"","binary_application":{"primary_binaries":{"count":0,"edges":[]},"id":"","platform":"","display_name":"","displayName":"","release_channels":{"count":0,"nodes":[]},"revisions":{"count":0,"nodes":[]},"organization":{"id":"","is_authorized_for_quest":false},"is_concept":false,"is_approved":false,"is_enterprise_enabled":false,"canonicalName":"","release_date":0,"viewer_has_preorder":false,"cover_landscape_image":{"uri":""},"cover_portrait_image":{"uri":""},"cover_square_image":{"uri":""},"screenshots":[],"supportedBinaries":{"count":0,"edges":[]}},"__isAppBinary":"","__isAppBinaryWithFileAsset":"","version_code":70300970,"versionCode":70300970,"created_date":1616013659,"binary_release_channels":{"count":0,"nodes":[{"id":"563338427502637","channel_name":"LIVE","latest_supported_binary":{"id":"","version":"","platform":"","file_name":"","uri":"","change_log":"","changeLog":"","richChangeLog":"","binary_application":{"primary_binaries":{"count":0,"edges":[]},"id":"","platform":"","display_name":"","displayName":"","release_channels":{"count":0,"nodes":[]},"revisions":{"count":0,"nodes":[]},"organization":{"id":"","is_authorized_for_quest":false},"is_concept":false,"is_approved":false,"is_enterprise_enabled":false,"canonicalName":"","release_date":0,"viewer_has_preorder":false,"cover_landscape_image":{"uri":""},"cover_portrait_image":{"uri":""},"cover_square_image":{"uri":""},"screenshots":[],"supportedBinaries":{"count":0,"edges":[]}},"__isAppBinary":"","__isAppBinaryWithFileAsset":"","version_code":0,"versionCode":0,"created_date":0,"binary_release_channels":null,"__typename":""}}]},"__typename":"AndroidBinary"}},{"node":{"id":"4897761453629021","version":"6.34.2","platform":"","file_name":"oculus-prod-sling-armeabi-v7a-release-6.34.2.apk","uri":"","change_log":"","changeLog":"","richChangeLog":"","binary_application":{"primary_binaries":{"count":0,"edges":[]},"id":"","platform":"","display_name":"","displayName":"","release_channels":{"count":0,"nodes":[]},"revisions":{"count":0,"nodes":[]},"organization":{"id":"","is_authorized_for_quest":false},"is_concept":false,"is_approved":false,"is_enterprise_enabled":false,"canonicalName":"","release_date":0,"viewer_has_preorder":false,"cover_landscape_image":{"uri":""},"cover_portrait_image":{"uri":""},"cover_square_image":{"uri":""},"screenshots":[],"supportedBinaries":{"count":0,"edges":[]}},"__isAppBinary":"","__isAppBinaryWithFileAsset":"","version_code":63400020,"versionCode":63400020,"created_date":1604960774,"binary_release_channels":{"count":0,"nodes":[{"id":"563338427502637","channel_name":"LIVE","latest_supported_binary":{"id":"","version":"","platform":"","file_name":"","uri":"","change_log":"","changeLog":"","richChangeLog":"","binary_application":{"primary_binaries":{"count":0,"edges":[]},"id":"","platform":"","display_name":"","displayName":"","release_channels":{"count":0,"nodes":[]},"revisions":{"count":0,"nodes":[]},"organization":{"id":"","is_authorized_for_quest":false},"is_concept":false,"is_approved":false,"is_enterprise_enabled":false,"canonicalName":"","release_date":0,"viewer_has_preorder":false,"cover_landscape_image":{"uri":""},"cover_portrait_image":{"uri":""},"cover_square_image":{"uri":""},"screenshots":[],"supportedBinaries":{"count":0,"edges":[]}},"__isAppBinary":"","__isAppBinaryWithFileAsset":"","version_code":0,"versionCode":0,"created_date":0,"binary_release_channels":null,"__typename":""}}]},"__typename":"AndroidBinary"}},{"node":{"id":"4590701267668376","version":"6.29.8","platform":"","file_name":"oculus-prod-sling-armeabi-v7a-release-6.29-8-Quest.apk","uri":"","change_log":"","changeLog":"","richChangeLog":"","binary_application":{"primary_binaries":{"count":0,"edges":[]},"id":"","platform":"","display_name":"","displayName":"","release_channels":{"count":0,"nodes":[]},"revisions":{"count":0,"nodes":[]},"organization":{"id":"","is_authorized_for_quest":false},"is_concept":false,"is_approved":false,"is_enterprise_enabled":false,"canonicalName":"","release_date":0,"viewer_has_preorder":false,"cover_landscape_image":{"uri":""},"cover_portrait_image":{"uri":""},"cover_square_image":{"uri":""},"screenshots":[],"supportedBinaries":{"count":0,"edges":[]}},"__isAppBinary":"","__isAppBinaryWithFileAsset":"","version_code":62900080,"versionCode":62900080,"created_date":1599698779,"binary_release_channels":{"count":0,"nodes":[{"id":"563338427502637","channel_name":"LIVE","latest_supported_binary":{"id":"","version":"","platform":"","file_name":"","uri":"","change_log":"","changeLog":"","richChangeLog":"","binary_application":{"primary_binaries":{"count":0,"edges":[]},"id":"","platform":"","display_name":"","displayName":"","release_channels":{"count":0,"nodes":[]},"revisions":{"count":0,"nodes":[]},"organization":{"id":"","is_authorized_for_quest":false},"is_concept":false,"is_approved":false,"is_enterprise_enabled":false,"canonicalName":"","release_date":0,"viewer_has_preorder":false,"cover_landscape_image":{"uri":""},"cover_portrait_image":{"uri":""},"cover_square_image":{"uri":""},"screenshots":[],"supportedBinaries":{"count":0,"edges":[]}},"__isAppBinary":"","__isAppBinaryWithFileAsset":"","version_code":0,"versionCode":0,"created_date":0,"binary_release_channels":null,"__typename":""}}]},"__typename":"AndroidBinary"}},{"node":{"id":"2793427500729104","version":"1.1.24","platform":"","file_name":"prod-sling-1.1.24-armeabi.apk","uri":"","change_log":"","changeLog":"","richChangeLog":"","binary_application":{"primary_binaries":{"count":0,"edges":[]},"id":"","platform":"","display_name":"","displayName":"","release_channels":{"count":0,"nodes":[]},"revisions":{"count":0,"nodes":[]},"organization":{"id":"","is_authorized_for_quest":false},"is_concept":false,"is_approved":false,"is_enterprise_enabled":false,"canonicalName":"","release_date":0,"viewer_has_preorder":false,"cover_landscape_image":{"uri":""},"cover_portrait_image":{"uri":""},"cover_square_image":{"uri":""},"screenshots":[],"supportedBinaries":{"count":0,"edges":[]}},"__isAppBinary":"","__isAppBinaryWithFileAsset":"","version_code":10100240,"versionCode":10100240,"created_date":1556561131,"binary_release_channels":{"count":0,"nodes":[{"id":"563338427502637","channel_name":"LIVE","latest_supported_binary":{"id":"","version":"","platform":"","file_name":"","uri":"","change_log":"","changeLog":"","richChangeLog":"","binary_application":{"primary_binaries":{"count":0,"edges":[]},"id":"","platform":"","display_name":"","displayName":"","release_channels":{"count":0,"nodes":[]},"revisions":{"count":0,"nodes":[]},"organization":{"id":"","is_authorized_for_quest":false},"is_concept":false,"is_approved":false,"is_enterprise_enabled":false,"canonicalName":"","release_date":0,"viewer_has_preorder":false,"cover_landscape_image":{"uri":""},"cover_portrait_image":{"uri":""},"cover_square_image":{"uri":""},"screenshots":[],"supportedBinaries":{"count":0,"edges":[]}},"__isAppBinary":"","__isAppBinaryWithFileAsset":"","version_code":0,"versionCode":0,"created_date":0,"binary_release_channels":null,"__typename":""}}]},"__typename":"AndroidBinary"}}]},"latest_supported_binary":{"binary_application":{"display_name":""}},"appName":"Sling TV","headset":"MONTEREY","squareImage":"https://scontent.oculuscdn.com/v/t64.5771-25/q92/s720x720/39031431_330441517654442_8185376315126317056_n.jpg?_nc_cat=100\u0026ccb=1-5\u0026_nc_sid=79b88e\u0026_nc_ohc=DPduqc1QaiIAX-p1wo7\u0026_nc_ht=scontent.oculuscdn.com\u0026oh=00_AT8tMoe8A4PKnyiqafw1ADxaSflGhyZd3u4em4En_Duz9g\u0026oe=6202E125","id":"2703538566384665"}}}