{"data":{"node":{"binaries":{"edges":[{"node":{"change_log":"N/A","id":"4179069498842025","version":"1.19.6","version_code":145,"created_date":1626652479}},{"node":{"change_log":"N/A","id":"4037557216326588","version":"1.19.4","version_code":142,"created_date":1622250618}},{"node":{"change_log":"N/A","id":"4037280946354215","version":"1.19.4","version_code":141,"created_date":1622241793}},{"node":{"change_log":"N/A","id":"4005377459544564","version":"1.19.3","version_code":134,"created_date":1621346475}},{"node":{"change_log":"N/A","id":"3993205497428427","version":"1.19.2","version_code":133,"created_date":1621003319}},{"node":{"change_log":"N/A","id":"3987232061359104","version":"1.19.1","version_code":132,"created_date":1620833863}},{"node":{"change_log":"N/A","id":"3972674126148231","version":"1.19.0","version_code":128,"created_date":1620424546}},{"node":{"change_log":"N/A","id":"3972158372866473","version":"1.19.0","version_code":126,"created_date":1620410628}},{"node":{"change_log":"N/A","id":"3801579589924353","version":"1.18.17","version_code":111,"created_date":1615305438}},{"node":{"change_log":"N/A","id":"3778527118896267","version":"1.18.16","version_code":110,"created_date":1614511925}},{"node":{"change_log":"N/A","id":"3775441209204858","version":"1.18.15","version_code":109,"created_date":1614416895}},{"node":{"change_log":"N/A","id":"3773148592767453","version":"1.18.15","version_code":108,"created_date":1614373106}},{"node":{"change_log":"N/A","id":"3740401709375475","version":"1.18.14","version_code":104,"created_date":1613478723}},{"node":{"change_log":"N/A","id":"3733998643349115","version":"1.18.13","version_code":102,"created_date":1613250605}},{"node":{"change_log":"N/A","id":"3714157405333239","version":"1.18.12","version_code":101,"created_date":1612588131}},{"node":{"change_log":"N/A","id":"3684685178280462","version":"1.18.11","version_code":97,"created_date":1611602606}},{"node":{"change_log":"N/A","id":"3668467886568858","version":"1.18.10","version_code":96,"created_date":1611075499}},{"node":{"change_log":"N/A","id":"3631269180288729","version":"1.18.9","version_code":94,"created_date":1609895404}},{"node":{"change_log":"N/A","id":"3625753890840258","version":"1.18.8","version_code":93,"created_date":1609689379}},{"node":{"change_log":"N/A","id":"3621985461217101","version":"1.18.7","version_code":92,"created_date":1609549634}},{"node":{"change_log":"N/A","id":"3569817739767207","version":"1.18.6","version_code":87,"created_date":1607721244}},{"node":{"change_log":"N/A","id":"3551786971570284","version":"1.18.4","version_code":82,"created_date":1607113607}},{"node":{"change_log":"N/A","id":"3537928949622753","version":"1.18.3","version_code":81,"created_date":1606681226}},{"node":{"change_log":"N/A","id":"3532793103469671","version":"1.18.2","version_code":80,"created_date":1606518144}},{"node":{"change_log":"N/A","id":"3532367650178883","version":"1.18.2","version_code":78,"created_date":1606504035}},{"node":{"change_log":"N/A","id":"3524193720996276","version":"1.18.1","version_code":75,"created_date":1606242829}},{"node":{"change_log":"N/A","id":"3436882389727410","version":"1.17.10","version_code":63,"created_date":1603476660}},{"node":{"change_log":"N/A","id":"3433679676714348","version":"1.17.9","version_code":62,"created_date":1603379990}},{"node":{"change_log":"N/A","id":"3415366648545651","version":"1.17.8","version_code":61,"created_date":1602776087}},{"node":{"change_log":"N/A","id":"3409972795751703","version":"1.17.7","version_code":60,"created_date":1602605771}},{"node":{"change_log":"N/A","id":"3397718700310446","version":"1.17.6","version_code":59,"created_date":1602253129}},{"node":{"change_log":"N/A","id":"3376216109127372","version":"1.17.5","version_code":58,"created_date":1601661411}},{"node":{"change_log":"N/A","id":"3357162224366094","version":"1.17.4","version_code":54,"created_date":1601133533}},{"node":{"change_log":"N/A","id":"3355985717817078","version":"1.17.4","version_code":53,"created_date":1601102566}},{"node":{"change_log":"N/A","id":"3351481014934215","version":"1.17.3","version_code":49,"created_date":1600973778}},{"node":{"change_log":"N/A","id":"3288643877884596","version":"1.17.2","version_code":48,"created_date":1599236682}},{"node":{"change_log":"N/A","id":"3285003394915311","version":"1.17.1","version_code":47,"created_date":1599136375}},{"node":{"change_log":"N/A","id":"3279427558806228","version":"1.17.0","version_code":45,"created_date":1598984546}},{"node":{"change_log":"N/A","id":"3143807505701568","version":"1.16.0","version_code":36,"created_date":1594977077}},{"node":{"change_log":"N/A","id":"3097963283619324","version":"1.15.5","version_code":35,"created_date":1593523219}},{"node":{"change_log":"N/A","id":"3067780833304236","version":"1.15.3","version_code":33,"created_date":1592578127}},{"node":{"change_log":"N/A","id":"3050060468409606","version":"1.15.1","version_code":31,"created_date":1591988452}},{"node":{"change_log":"N/A","id":"3047723238643329","version":"1.15.0","version_code":30,"created_date":1591909966}},{"node":{"change_log":"N/A","id":"3011508772264776","version":"1.14.2","version_code":25,"created_date":1590667684}},{"node":{"change_log":"N/A","id":"2992717684143885","version":"1.14.1","version_code":24,"created_date":1589983502}}]},"latest_supported_binary":{"binary_application":{"display_name":""}},"appName":"Premium Bowling","headset":"MONTEREY","squareImage":"https://scontent.oculuscdn.com/v/t64.5771-25/q92/s720x720/38974480_248406549483372_8756371377948196864_n.jpg?_nc_cat=101\u0026ccb=1-5\u0026_nc_sid=79b88e\u0026_nc_ohc=2YJLFTp2R8MAX-lSPrN\u0026_nc_ht=scontent.oculuscdn.com\u0026oh=23a09e406668ddc04f5587bb7f23d67c\u0026oe=61344938","id":"2773034772778845"}}}